<?xml version="1.0"?>
<!DOCTYPE xliff PUBLIC "-//XLIFF//DTD XLIFF//EN" "http://www.oasis-open.org/committees/xliff/documents/xliff.dtd">
<xliff version="1.0">
<file original="kipus-en.xml" source-language="en-US" datatype="plaintext">
<header/>
<body>

<trans-unit id="add"><source>Add entry</source></trans-unit>
<trans-unit id="admin"><source>Admin</source></trans-unit>
<trans-unit id="admin_advanced"><source>Advanced options</source></trans-unit>
<trans-unit id="admin_autocreate"><source>Create Books with autocreate flag</source></trans-unit>
<trans-unit id="admin_sync"><source>Synchronize with the server</source></trans-unit>
<trans-unit id="admin_syncBookDef"><source>Download book definitions and helper-tables</source></trans-unit>
<trans-unit id="alreadyExists"><source>Entry already exists</source></trans-unit>
<trans-unit id="appInstalled"><source>This page was successfully installed as an application.&lt;br&gt;
Please close this browser page and continue to use the app on the home screen.</source></trans-unit>
<trans-unit id="back"><source>Back</source></trans-unit>
<trans-unit id="book"><source>Book</source></trans-unit>
<trans-unit id="bookDefFailed"><source>Data partially downloaded</source></trans-unit>
<trans-unit id="bookDefResult"><source>Got {1} books, {2} pages, {3} attributes</source></trans-unit>
<trans-unit id="bookHeader"><source>Book header</source></trans-unit>
<trans-unit id="caErr1"><source>Action Text Missing</source></trans-unit>
<trans-unit id="caShowClosed"><source>(closed entries)</source></trans-unit>
<trans-unit id="caShowOpen"><source>(open entries)</source></trans-unit>
<trans-unit id="cancel"><source>Cancel</source></trans-unit>
<trans-unit id="changeuser"><source>Change User</source></trans-unit>
<trans-unit id="checkDateStartEnd"><source>End date is before start date</source></trans-unit>
<trans-unit id="checkLength"><source>{1} is too long</source></trans-unit>
<trans-unit id="checkMandatory"><source>{1} is mandatory</source></trans-unit>
<trans-unit id="checkNumBoundery"><source>Boundery ({2}) exceeded for {1}</source></trans-unit>
<trans-unit id="checkRegexp"><source>{1} check failed</source></trans-unit>
<trans-unit id="clear"><source>Clear</source></trans-unit>
<trans-unit id="computedAreaToSmall"><source>The computed area is &lt; 1 ㎡, the distance between shape points is too small.&lt;br&gt;Shape was removed.</source></trans-unit>
<trans-unit id="connecting"><source>Connecting to kipus server...</source></trans-unit>
<trans-unit id="correctiveAction"><source>Corrective action</source></trans-unit>
<trans-unit id="create"><source>Create</source></trans-unit>
<trans-unit id="createNotAllowed"><source>Permission denied</source></trans-unit>
<trans-unit id="debugComment"><source>Add comment</source></trans-unit>
<trans-unit id="debugInfo"><source>Check debug messages</source></trans-unit>
<trans-unit id="delAll"><source>All data on this client will be deleted, unsynchronized data gets lost!</source></trans-unit>
<trans-unit id="deleteRow"><source>Delete entry</source></trans-unit>
<trans-unit id="deleteRowReally"><source>This will delete ALL data entered for this entry permanently.&lt;br&gt;Are you sure you want to delete this entry?&lt;br&gt;To discard only the last changes without saving them, use the back arrow on the top left of the screen.</source></trans-unit>
<trans-unit id="deleteRowReallyCancel"><source>NO, keep this entry</source></trans-unit>
<trans-unit id="deleteRowReallyOK"><source>YES, delete this entry</source></trans-unit>
<trans-unit id="download"><source>Load</source></trans-unit>
<trans-unit id="discardChanges"><source>Discard the changed data?</source></trans-unit>
<trans-unit id="downloadMD_picture"><source>Download pictures too</source></trans-unit>
<trans-unit id="downloadMD_time"><source>Time period</source></trans-unit>
<trans-unit id="downloadMD_time1m"><source>last Month</source></trans-unit>
<trans-unit id="downloadMD_time1y"><source>last Year</source></trans-unit>
<trans-unit id="downloadMD_timeAll"><source>Everything</source></trans-unit>
<trans-unit id="downloadMyData"><source>Download my data from the server</source></trans-unit>
<trans-unit id="downloadProgram"><source>Loading program files:&lt;br&gt;{1} of {2}</source></trans-unit>
<trans-unit id="downloadProgramError"><source>Loading program failed:&lt;br&gt;{1}&lt;br&gt;Try to reload.</source></trans-unit>
<trans-unit id="downloadSaving"><source>Saving table {1}</source></trans-unit>
<trans-unit id="downloadServer"><source>Getting data from server</source></trans-unit>
<trans-unit id="enoperm"><source>Permission denied</source></trans-unit>
<trans-unit id="filesizeExceeded"><source>Max Filesize exceeded (maxsize={1} bytes).</source></trans-unit>
<trans-unit id="gpsAccuracy"><source>Accuracy</source></trans-unit>
<trans-unit id="gpsArea"><source>Calculated area: {1} ha</source></trans-unit>
<trans-unit id="gpsAverage"><source>average of {1} points</source></trans-unit>
<trans-unit id="gpsDeleteShape"><source>Delete drawn shape</source></trans-unit>
<trans-unit id="gpsGetLoc"><source>Get current location from GPS</source></trans-unit>
<trans-unit id="gpsIgnComp"><source>Ignore computed value</source></trans-unit>
<trans-unit id="gpsInit"><source>GPS initializing - this may take a few, in rare cases up to 10, minutes, please be patient. Avoid standing under trees and rainy weather to get quick initialization.
</source></trans-unit>
<trans-unit id="gpsReceiving"><source>Receiving GPS Data</source></trans-unit>
<trans-unit id="gpsTrackButton"><source>Track field point from GPS</source></trans-unit>
<trans-unit id="gpsUseGM"><source>Use Google-Maps</source></trans-unit>
<trans-unit id="gpsUseGMHelp1"><source>Note: Google-Maps needs internet connection</source></trans-unit>
<trans-unit id="gpsUseGMHelp2"><source>Drag the pin and drop it to the desired location</source></trans-unit>
<trans-unit id="helpTextLoginName"><source>Enter your login name here</source></trans-unit>
<trans-unit id="helpTextPassword"><source>Enter your password here</source></trans-unit>
<trans-unit id="home"><source>Overview</source></trans-unit>
<trans-unit id="importClientDBReady"><source>Client database import finished</source></trans-unit>
<trans-unit id="inputFile"><source>Select File</source></trans-unit>
<trans-unit id="inputPhoto"><source>Select Photo</source></trans-unit>
<trans-unit id="langButton"><source>Set language</source></trans-unit>
<trans-unit id="langLabel"><source>Language</source></trans-unit>
<trans-unit id="langTitle"><source>Select language</source></trans-unit>
<trans-unit id="leaveApp"><source>Leaving the app (KIPUS)</source></trans-unit>
<trans-unit id="loadImg"><source>Downloading image {1}</source></trans-unit>
<trans-unit id="locked"><source>Data entry locked</source></trans-unit>
<trans-unit id="login"><source>Login</source></trans-unit>
<trans-unit id="loginName"><source>Login Name</source></trans-unit>
<trans-unit id="loginOffline"><source>ready to operate offline</source></trans-unit>
<trans-unit id="loginOnline"><source>online operation only</source></trans-unit>
<trans-unit id="moreEntries"><source>{1} more entries</source></trans-unit>
<trans-unit id="moreEntry"><source>one more entry</source></trans-unit>
<trans-unit id="multiPicDone"><source>Done</source></trans-unit>
<trans-unit id="networkErr"><source>Network Error, please check the Internet Connection.</source></trans-unit>
<trans-unit id="networkNeeded"><source>needs internet connection</source></trans-unit>
<trans-unit id="newBook"><source>New book</source></trans-unit>
<trans-unit id="no"><source>No</source></trans-unit>
<trans-unit id="noBodyPage"><source>No page definition available</source></trans-unit>
<trans-unit id="noBookDef"><source>No book definition available</source></trans-unit>
<trans-unit id="noSel"><source>Nothing selected</source></trans-unit>
<trans-unit id="numHelp"><source>Number between {1} and {2}</source></trans-unit>
<trans-unit id="numHelp2"><source>Number between {1} and {2}, with {3} decimal places</source></trans-unit>
<trans-unit id="ok"><source>Ok</source></trans-unit>
<trans-unit id="password"><source>Password</source></trans-unit>
<trans-unit id="programUpdate"><source>Check for program update</source></trans-unit>
<trans-unit id="pushBlocked"><source>Push subscription is blocked</source></trans-unit>
<trans-unit id="pushNotSupported"><source>Push is not supported!</source></trans-unit>
<trans-unit id="pushPrompt"><source>Do you want to receive push messages?&lt;br&gt;You can always disable or enable push messages in the menu.</source></trans-unit>
<trans-unit id="pushSubscribe"><source>Subscribe to push messages</source></trans-unit>
<trans-unit id="pushUnsubscribe"><source>Unsubscribe to push messages</source></trans-unit>
<trans-unit id="pwRequired"><source>Password protected</source></trans-unit>
<trans-unit id="pw_change"><source>Change Password</source></trans-unit>
<trans-unit id="pw_changed"><source>Password changed</source></trans-unit>
<trans-unit id="pw_do"><source>Change</source></trans-unit>
<trans-unit id="pw_dontmatch"><source>Passwords dont match</source></trans-unit>
<trans-unit id="pw_newpw"><source>New Password</source></trans-unit>
<trans-unit id="pw_newpw2"><source>Retype Password</source></trans-unit>
<trans-unit id="pw_oldpw"><source>Old Password</source></trans-unit>
<trans-unit id="pw_tooshort"><source>New password is too short</source></trans-unit>
<trans-unit id="pw_wrongold"><source>Old password is incorrect</source></trans-unit>
<trans-unit id="qrBadPrefix"><source>Wrong QR code detected (does not contain the expected prefix)</source></trans-unit>
<trans-unit id="qrBadRegexp"><source>Wrong QR code detected (configured validation failed)</source></trans-unit>
<trans-unit id="qrScan"><source>Scan</source></trans-unit>
<trans-unit id="qrScanAbort"><source>Abort scanning</source></trans-unit>
<trans-unit id="quizBackToStart"><source>Do you want to go back to start?</source></trans-unit>
<trans-unit id="quizCancel"><source>Do you really want to end the quiz? Progress will not be saved.</source></trans-unit>
<trans-unit id="quizCheck"><source>Check answer</source></trans-unit>
<trans-unit id="quizPleaseChoose"><source>Please choose an answer.</source></trans-unit>
<trans-unit id="quizQuestion"><source>Question {1}/{2}</source></trans-unit>
<trans-unit id="quizResult100"><source>Perfect! You know everything about this topic. Please don't forget to share your knowledge.</source></trans-unit>
<trans-unit id="quizResultUpTo100"><source>Fantastic! You knew most of the answers, you have a very good knowledge of this topic.</source></trans-unit>
<trans-unit id="quizResultUpTo25"><source>Don't worry, no-one is born a master. Just look at the questions again in the learning mode to improve your knowledge, and then try again!</source></trans-unit>
<trans-unit id="quizResultUpTo50"><source>Good work! Maybe you can try the learning mode to close some gaps in your knowledge.</source></trans-unit>
<trans-unit id="quizResultUpTo75"><source>Very good! More than half of the correct answers. Keep learning to achieve even better results.</source></trans-unit>
<trans-unit id="quizResultsAnswered"><source>You have answered {1} questions out of {2} correctly.</source></trans-unit>
<trans-unit id="quizResultsHeader"><source>Your results</source></trans-unit>
<trans-unit id="quizResultsNote"><source>Note: you have left {1} questions open.</source></trans-unit>
<trans-unit id="quizSave"><source>Save answer</source></trans-unit>
<trans-unit id="quizTocHeader"><source>Learn the answers</source></trans-unit>
<trans-unit id="quizTocText"><source>To refresh your knowledge, you can read all the questions and check your answers before taking the test.</source></trans-unit>
<trans-unit id="readonly"><source>Entry is readonly</source></trans-unit>
<trans-unit id="ready"><source>Ready</source></trans-unit>
<trans-unit id="regionLabel"><source>Region</source></trans-unit>
<trans-unit id="resetDatabase"><source>Clear data (unsynced data will be lost)</source></trans-unit>
<trans-unit id="resetDatabaseDone"><source>App Data cleared.&lt;br&gt;
To restart, just reload the app (swipe down) to download the app from scratch.&lt;br&gt;&lt;br&gt;
If you do not intend to reinstall the app, we recommend you also uninstall the app by deleting the app from the home screen.
</source></trans-unit>
<trans-unit id="resetSync"><source>Reset sync status</source></trans-unit>
<trans-unit id="resumeQuiz"><source>Resume the test</source></trans-unit>
<trans-unit id="save"><source>Save</source></trans-unit>
<trans-unit id="settingsButton"><source>Update settings</source></trans-unit>
<trans-unit id="settingsTitle"><source>User settings</source></trans-unit>
<trans-unit id="signatureEnter"><source>Enter Signature</source></trans-unit>
<trans-unit id="startQuiz"><source>Take the test</source></trans-unit>
<trans-unit id="startQuizHeader"><source>Test your knowledge</source></trans-unit>
<trans-unit id="startQuizText"><source>Answer all questions to find out how good your knowledge is.</source></trans-unit>
<trans-unit id="statistics"><source>Statistics</source></trans-unit>
<trans-unit id="structExec"><source>Structural change: {1}</source></trans-unit>
<trans-unit id="sync"><source>Sync</source></trans-unit>
<trans-unit id="syncBookDef"><source>Download book definitions and helper-tables</source></trans-unit>
<trans-unit id="syncBusy"><source>Another Sync operation is in progress. Please try again later.</source></trans-unit>
<trans-unit id="syncDataCollect"><source>Collect data...</source></trans-unit>
<trans-unit id="syncDetails"><source>Technical details</source></trans-unit>
<trans-unit id="syncFailed"><source>Sync not possible, problems with the internet connection?</source></trans-unit>
<trans-unit id="syncFinished"><source>Sync finished</source></trans-unit>
<trans-unit id="syncGotData"><source>Got new data</source></trans-unit>
<trans-unit id="syncImgRem"><source>To send: {1} images/documents</source></trans-unit>
<trans-unit id="syncNewProg"><source>Program will be updated.</source></trans-unit>
<trans-unit id="syncNoData"><source>No data to send</source></trans-unit>
<trans-unit id="syncNoDef"><source>No definition changes</source></trans-unit>
<trans-unit id="syncNoProg"><source>Program is up to date</source></trans-unit>
<trans-unit id="syncSend"><source>Sending data to server...</source></trans-unit>
<trans-unit id="syncTimeout"><source>Background sync of images timed out. No need to worry.</source></trans-unit>
<trans-unit id="swRegisterError"><source>App could not be registered as a progressive web app, fallback to traditional app mode.&lt;br&gt;
Some functionalities like receiving push notifications or add to home screen prompt do not work in the traditional app mode.</source></trans-unit>
<trans-unit id="tableCopy"><source>Import the list</source></trans-unit>
<trans-unit id="tableCopyClear"><source>Delete the list</source></trans-unit>
<trans-unit id="tableCopyEmpty"><source>No data found to copy</source></trans-unit>
<trans-unit id="takePhoto"><source>Take photo</source></trans-unit>
<trans-unit id="timeGroupEmpty"><source>{1} list is empty, please fill it first</source></trans-unit>
<trans-unit id="unsupportedImage"><source>Only photos of type jpeg are supported</source></trans-unit>
<trans-unit id="upload"><source>Upload</source></trans-unit>
<trans-unit id="uploadClientDB"><source>Upload client database (to help debugging)</source></trans-unit>
<trans-unit id="uploadClientDBReady"><source>Client database was uploaded to {1}</source></trans-unit>
<trans-unit id="uploadData"><source>Upload entered data</source></trans-unit>
<trans-unit id="uploadReady"><source>Upload finished</source></trans-unit>
<trans-unit id="userPreferences"><source>User preferences</source></trans-unit>
<trans-unit id="videoDownload"><source>Download videos for storage on your device</source></trans-unit>
<trans-unit id="viewEntry"><source>View entries</source></trans-unit>
<trans-unit id="yes"><source>Yes</source></trans-unit>

</body>
</file>
</xliff>
