<?xml version="1.0"?><!DOCTYPE xliff PUBLIC "-//XLIFF//DTD XLIFF//EN" "http://www.oasis-open.org/committees/xliff/documents/xliff.dtd"><xliff version="1.0">
  <file original="admin_vi.xml" source-language="en-US" target-language="vi" datatype="plaintext">
    <header/>
    <body>
      <trans-unit id="add_permission_column">
        <source>Add permission column</source>
      </trans-unit>
      <trans-unit id="adminright_add_button">
        <source>Add Admin right</source>
      </trans-unit>
      <trans-unit id="bd_recomputeScore">
        <source>Recompute score</source>
      </trans-unit>
      <trans-unit id="compare_button">
        <source>Start compare Mode</source>
      </trans-unit>
      <trans-unit id="datarow_jump_to_parentbook">
        <source>Go to parent book</source>
      </trans-unit>
      <trans-unit id="external_create_button">
        <source>Add external table</source>
      </trans-unit>
      <trans-unit id="external_update_button">
        <source>Update external table</source>
      </trans-unit>
      <trans-unit id="mn_bookdata_button">
        <source>Manage bookdata</source>
      </trans-unit>
      <trans-unit id="nav_brand">
        <source>Admin Dashboard</source>
      </trans-unit>
      <trans-unit id="no">
        <source>NO</source>
      </trans-unit>
      <trans-unit id="option_NEWROW">
        <source>On a new row</source>
      </trans-unit>
      <trans-unit id="option_all">
        <source>Create BI data for all BODY pages</source>
      </trans-unit>
      <trans-unit id="option_alllast">
        <source>Create BI data for the last BODY page and for all BODY pages for historical analysis</source>
      </trans-unit>
      <trans-unit id="option_avg">
        <source>Build average for this attribute</source></trans-unit>
      <trans-unit id="option_body">
        <source>Body</source>
      </trans-unit>
      <trans-unit id="option_createonly">
        <source>Create Only</source>
      </trans-unit>
      <trans-unit id="option_critical">
        <source>Critical</source>
      </trans-unit>
      <trans-unit id="option_date">
        <source>Date</source>
        
      </trans-unit>
      <trans-unit id="option_dateTime">
        <source>DateTime</source>
      <target xml:lang="vi"/></trans-unit>
      <trans-unit id="option_dimension">
        <source>Attribute is a dimension</source></trans-unit>
      <trans-unit id="option_cp_lookup">
        <source>Cross-Project Lookup</source></trans-unit>
      <trans-unit id="option_external">
        <source>External</source></trans-unit>
      <trans-unit id="option_file">
        <source>Attachment (File)</source>
        
      </trans-unit>
      <trans-unit id="option_foto">
        <source>Photo</source></trans-unit>
        
      <trans-unit id="option_gps">
        <source>GPS</source></trans-unit>
      <trans-unit id="option_groupend">
        <source>Group End Marker</source><target xml:lang="vi"/></trans-unit>
      <trans-unit id="option_groupheader">
        <source>Group Header</source></trans-unit>
      <trans-unit id="option_header">
        <source>Header</source>
        
      </trans-unit>
      <trans-unit id="option_hidden">
        <source>Hidden</source></trans-unit>
      <trans-unit id="option_hiddentimestamp">
        <source>Hidden timestamp</source></trans-unit>
      <trans-unit id="option_important">
        <source>Important</source></trans-unit>
      <trans-unit id="option_info">
        <source>Info</source></trans-unit>
      <trans-unit id="option_infotext">
        <source>Infotext</source></trans-unit>
      <trans-unit id="option_last">
        <source>Create BI data for only the last BODY page</source></trans-unit>
      <trans-unit id="option_lookup">
        <source>Lookup</source>
        
      </trans-unit>
      <trans-unit id="option_mandatory">
        <source>Mandatory</source></trans-unit>
      <trans-unit id="option_mandatory_modifiablehdrcol">
        <source>Mandatory, modifiable header column</source></trans-unit>
      <trans-unit id="option_max">
        <source>Take maximum for this attribute</source></trans-unit>
      <trans-unit id="option_min">
        <source>Take minimum for this attribute</source></trans-unit>
      <trans-unit id="option_modifiablehdrcol">
        <source>Modifiable header column</source></trans-unit>
      <trans-unit id="option_multifromarg">
        <source>Multiple values from ConstraintParameter</source>
        
      </trans-unit>
      <trans-unit id="option_multifromtable">
        <source>Multiple values from table</source>
        
      </trans-unit>
      <trans-unit id="option_multiline">
        <source>Multi-Line Editor</source>
        
      </trans-unit>
      <trans-unit id="option_no">
        <source>NO</source>
        
      </trans-unit>
      <trans-unit id="option_none"><source>Do not include this attribute in BI</source></trans-unit>
      <trans-unit id="option_num">
        <source>Numerical</source>
        
      </trans-unit>
      <trans-unit id="option_pull">
        <source>PULL</source><target xml:lang="vi"/></trans-unit>
      <trans-unit id="option_push">
        <source>PUSH</source></trans-unit>
      <trans-unit id="option_qrcode">
        <source>QR code</source></trans-unit>
      <trans-unit id="option_quiz">
        <source>Quiz</source></trans-unit>
      <trans-unit id="option_readonly">
        <source>Read Only</source></trans-unit>
      <trans-unit id="option_regexp">
        <source>Regular Expression</source>
        
      </trans-unit>
      <trans-unit id="option_samerow">
        <source>On the same row</source></trans-unit>
      <trans-unit id="option_signature">
        <source>Signature</source></trans-unit>
      <trans-unit id="option_simple">
        <source>Simple</source></trans-unit>
      <trans-unit id="option_singlefromarg">
        <source>Single value from ConstraintParameter</source>
        
      </trans-unit>
      <trans-unit id="option_singlefromtable">
        <source>Single value from table</source>
        
      </trans-unit>
      <trans-unit id="option_sum">
        <source>Build sum for this attribute</source></trans-unit>
      <trans-unit id="option_tableCopy">
        <source>Table Copy</source><target xml:lang="vi"/></trans-unit>
      <trans-unit id="option_tableRows">
        <source>Table Rows</source></trans-unit>
      <trans-unit id="option_text">
        <source>Short-Text (one line)</source>
        
      </trans-unit>
      <trans-unit id="option_visible">
        <source>Visible</source></trans-unit>
      <trans-unit id="option_yes">
        <source>YES</source>
        
      </trans-unit>
      <trans-unit id="pd_create_button">
        <source>Add page</source>
        
      </trans-unit>
      <trans-unit id="pd_move2book"><source>Move to book</source></trans-unit>
      <trans-unit id="pd_update_button">
        <source>Update page</source>
        
      </trans-unit>
      <trans-unit id="pdattr_advanced"><source>Advanced</source></trans-unit>
      <trans-unit id="pdattr_create_button">
         <source>Add attribute</source>
         
      </trans-unit>
      <trans-unit id="pdattr_rename_button"><source>Rename column name</source></trans-unit>
      <trans-unit id="pdattr_renumber"><source>Renumber</source></trans-unit>
      <trans-unit id="pdattr_update_button"><source>Update attribute</source></trans-unit>
      <trans-unit id="pdattrs_from_page_create_button"><source>Add attributes from page</source></trans-unit>
      <trans-unit id="pfile_upload_button"><source>Upload file to project</source></trans-unit>
      <trans-unit id="project_advanced">
          <source>Advanced</source>
          
      </trans-unit>
      <trans-unit id="project_check_button">
         <source>Check project</source>
         
       </trans-unit>
        <trans-unit id="project_create_button">
           <source>Create project</source>
           
        </trans-unit>
        <trans-unit id="project_download_button"><source>Download project</source></trans-unit>
        <trans-unit id="project_import_button"><source>Import project</source></trans-unit>
        <trans-unit id="project_project_button"><source>Update project</source></trans-unit>
        <trans-unit id="project_upload_pfile_button"><source>Upload file to project</source></trans-unit>
        <trans-unit id="project_xliff_button"><source>Generate translation</source></trans-unit>
        <trans-unit id="report_csvexport_button"><source>Download report table</source></trans-unit>
        <trans-unit id="report_hide_empty"><source><span class="showhide">Hide</span> empty rows/columns</source></trans-unit>
        <trans-unit id="report_svgexport_button"><source>Download charts as svg</source></trans-unit>
        <trans-unit id="resetlimit"><source>Show all rows (slow)</source></trans-unit>
        <trans-unit id="role_create_button"><source>Create role</source></trans-unit>
        <trans-unit id="role_update_button"><source>Update role</source></trans-unit>
        <trans-unit id="th_address">
            <source>Address</source>
           
        </trans-unit>
        <trans-unit id="th_adminrights"><source>Right</source></trans-unit>
        <trans-unit id="th_alwaysLogin"><source>Login always required</source></trans-unit>
        <trans-unit id="th_ampasswd"><source>Advanced menu password</source></trans-unit>
        <trans-unit id="th_attributelist">
           <source>Attribute List</source>
           
        </trans-unit>
        <trans-unit id="th_autocreate"><source>Autocreated</source><target xml:lang="vi"/></trans-unit>
        <trans-unit id="th_bookfilter"><source>Book Filter</source></trans-unit>
        <trans-unit id="th_userlist"><source>User List</source></trans-unit>
        <trans-unit id="th_biparams"><source>Business Intelligence (BI)</source><target xml:lang="vi"/></trans-unit>
        <trans-unit id="th_bookdefrights"><source>Book Filter / Regexp</source><target xml:lang="vi"/></trans-unit>
        <trans-unit id="th_bookid">
            <source>Book Definition Id</source>
           
        </trans-unit>
        <trans-unit id="th_booklist">
            <source>Book List</source>
           
        </trans-unit>
        <trans-unit id="th_booktitle">
            <source>Book Title</source>
           
        </trans-unit>
        <trans-unit id="th_bshowif"><source>Show If</source></trans-unit>
        <trans-unit id="th_changeNameTo"><source>Change Project Name To</source></trans-unit>
        <trans-unit id="th_checkOnly"><source>Check only, do not change anything</source></trans-unit>
        <trans-unit id="th_clear"><source>Clear</source>
           
        </trans-unit>
        <trans-unit id="th_columnmaxlength">
           <source>Column Max Length</source>
           
        </trans-unit>
        <trans-unit id="th_columnname">
        <source>Column Name</source>
           
        </trans-unit>
        <trans-unit id="th_columnorder">
           <source>Column Order</source>
           
        </trans-unit>
        <trans-unit id="th_columns"><source>Columns</source></trans-unit>
        <trans-unit id="th_condLabel"><source>Source</source></trans-unit>
        <trans-unit id="th_condValue"><source>Value</source></trans-unit>
        <trans-unit id="th_constraintparam">
           <source>Constraint Param</source>
           
        </trans-unit>
        <trans-unit id="th_constrainttype">
           <source>Constraint Type</source>
           
        </trans-unit>
        <trans-unit id="th_corrective"><source>Corrective Action</source></trans-unit>
        <trans-unit id="th_csvimport">
          <source>Table Csv file (mandatory)</source>
          
        <target xml:lang="vi"/></trans-unit>
        <trans-unit id="th_data"><source>Data</source></trans-unit>
        <trans-unit id="th_datadump">
           <source>Data Csv file (optional)</source>
           
        </trans-unit>
        <trans-unit id="th_defaultlang"><source>Default Language</source></trans-unit>
        <trans-unit id="th_defaultvalue">
           <source>Default Value</source>
           
        </trans-unit>
        <trans-unit id="th_delete">
          <source>Delete</source>
          
        <target xml:lang="vi">Xóa</target></trans-unit>
        <trans-unit id="th_remove">
          <source>Remove</source>
          
        </trans-unit>
        <trans-unit id="th_destination"><source>Destination</source><target xml:lang="vi"></target></trans-unit>
        <trans-unit id="th_direction"><source>Direction</source></trans-unit>
        <trans-unit id="th_directory"><source>Project Name</source></trans-unit>
        <trans-unit id="th_displayname"><source>Display Name</source>
           
        <target xml:lang="vi">Tên hiển thị</target></trans-unit>
        <trans-unit id="th_dst_table"><source>Destination Table</source></trans-unit>
        <trans-unit id="th_edit">
           <source>Edit</source>
           
        <target xml:lang="vi">Chỉnh sửa</target></trans-unit>
        <trans-unit id="th_email">
           <source>Email address</source>
           
        <target xml:lang="vi">Địa chỉ email</target></trans-unit>
        <trans-unit id="th_extension"><source>File Extension</source><target xml:lang="vi"/></trans-unit>
        <trans-unit id="th_externalid"><source>External Id</source></trans-unit>
        <trans-unit id="th_externallist"><source>External Tables</source></trans-unit>
        <trans-unit id="th_filename"><source>File Name</source></trans-unit>
        <trans-unit id="th_filesize"><source>File Size</source></trans-unit>
        <trans-unit id="th_fileslist"><source>Files List</source></trans-unit>
        <trans-unit id="th_filter"><source>Filter</source></trans-unit>
        <trans-unit id="th_gluewithnext"><source>Glue with next</source></trans-unit>
        <trans-unit id="th_helptext">
           <source>Help Text</source>
           
        </trans-unit>
        <trans-unit id="th_hidden"><source>Hidden</source></trans-unit>
        <trans-unit id="th_i18n"><source>Translation needed</source></trans-unit>
        <trans-unit id="th_importOverwrite">
           <source>Overwrite by Import</source>
           
        </trans-unit>
        <trans-unit id="th_import_bd">
           <source>Kipus file (mandatory)</source>
           
        </trans-unit>
        <trans-unit id="th_import_project"><source>Project zip file (mandatory)</source></trans-unit>
        <trans-unit id="th_include_userdata"><source>Include user-data</source></trans-unit>
        <trans-unit id="th_inputtype"><source>Input Type</source></trans-unit>
        <trans-unit id="th_isdefault"><source>Default</source></trans-unit>
        <trans-unit id="th_offline_active"><source>Offline Active</source></trans-unit>
        <trans-unit id="th_isoffline"><source>Offline</source><target xml:lang="vi"/></trans-unit>
        <trans-unit id="th_javascriptonchange"><source>Javascript on change</source></trans-unit>
        <trans-unit id="th_javascriptonsave"><source>Javascript on save</source></trans-unit>
        <trans-unit id="th_lastsync"><source>Last sync</source>
           
        <target xml:lang="vi">Đồng bộ lần cuối</target></trans-unit>
        <trans-unit id="th_login"><source>Login</source>
           
        <target xml:lang="vi">Tên đăng nhập</target></trans-unit>
        <trans-unit id="th_longhelp"><source>Long help (HTML)</source></trans-unit>
        <trans-unit id="th_longtitle"><source>Long Title</source></trans-unit>
        <trans-unit id="th_lvlabel"><source>Last</source></trans-unit>
        <trans-unit id="th_modified">
           <source>Date modified</source>
           
        </trans-unit>
        <trans-unit id="th_modified_by">
           <source>Modified by</source>
           
        </trans-unit>
        <trans-unit id="th_book_name"><source>Book Name</source></trans-unit>
        <trans-unit id="th_name"><source>Name</source></trans-unit>
        <trans-unit id="th_order">
           <source>Order</source>
           
        </trans-unit>
        <trans-unit id="th_overwriteLocal"><source>Overwrite data even if marked as "Overwrite by Import: NO"</source></trans-unit>
        <trans-unit id="th_pageid">
           <source>Page Definition Id</source>
           
        </trans-unit>
        <trans-unit id="th_pagelist">
           <source>Page List</source>
           
        </trans-unit>
        <trans-unit id="th_pagetype">
           <source>Page Type</source>
           
        </trans-unit>
        <trans-unit id="th_parentbookid"><source>Parent Book</source></trans-unit>
        <trans-unit id="th_lang">
           <source>Language</source>
           
        </trans-unit>
        <trans-unit id="th_passwd"><source>Password</source>
           
        </trans-unit>
        <trans-unit id="th_passwd2"><source>Password Confirm</source>
           
        </trans-unit>
        <trans-unit id="th_permcol"><source>Column</source></trans-unit>
        <trans-unit id="th_permcollist"><source>Permission Columns</source></trans-unit>
        <trans-unit id="th_permission"><source>Permission</source></trans-unit>
        <trans-unit id="th_placeholder"><source>Placeholder</source></trans-unit>
        <trans-unit id="th_project_prefix"> 
           <source>Project Prefix</source>
           
        </trans-unit>
        <trans-unit id="th_prefix">
           <source>Prefix</source>
           
        </trans-unit>
        <trans-unit id="th_prightdef"><source>Permissions</source></trans-unit>
        <trans-unit id="th_project">
           <source>Project</source>
           
        </trans-unit>
        <trans-unit id="th_projectbook">
           <source>Project Book</source>
           
        </trans-unit>
        <trans-unit id="th_projectid"><source>Project Id</source></trans-unit>
        <trans-unit id="th_role"><source>Role</source></trans-unit>
        <trans-unit id="th_sel_project"><source>Select Project</source></trans-unit>
        <trans-unit id="th_conditions"><source>Conditions</source></trans-unit>
        <trans-unit id="th_permissions"><source>Permissions</source></trans-unit>
        <trans-unit id="th_projectlist"><source>Project List</source></trans-unit>
        <trans-unit id="th_projectname"><source>Project Name</source></trans-unit>
        <trans-unit id="th_replace_userdata"><source>Import body/header content, replace with existing</source></trans-unit>
        <trans-unit id="th_right"><source>Right</source></trans-unit>
        <trans-unit id="th_rights">
           <source>Rights</source>
           
        </trans-unit>
        <trans-unit id="th_roleid"><source>Role Id</source></trans-unit>
        <trans-unit id="th_rolename"><source>Name</source></trans-unit>
        <trans-unit id="th_roleparam"><source>Parameter</source></trans-unit>
        <trans-unit id="th_roletitle"><source>Title</source></trans-unit>
        <trans-unit id="th_rows"><source>Data Records approximation</source>
          
        </trans-unit>
        <trans-unit id="th_scoretype"><source>Score type</source></trans-unit>
        <trans-unit id="th_search">
          <source>Search</source>
          
        </trans-unit>
        <trans-unit id="th_shorttitle"><source>Short Title</source></trans-unit>
        <trans-unit id="th_showif"><source>Show if</source></trans-unit>
        <trans-unit id="th_sortby"><source>Sort by</source></trans-unit>
        <trans-unit id="th_sourcelang">
          <source>Source Language</source>
        </trans-unit>
        <trans-unit id="th_src_table"><source>Source Table</source></trans-unit>
        <trans-unit id="th_status"><source>Status</source><target xml:lang="vi">Tình trạng</target></trans-unit>
        <trans-unit id="th_subpageparam"><source>Sub-Page Param</source>
           
        </trans-unit>
        <trans-unit id="th_suffix">
          <source>Suffix/Unit</source>
        <target xml:lang="vi"/></trans-unit>
        <trans-unit id="th_tablename_displayname">
           <source>Table/Display Name</source>
        </trans-unit>
        <trans-unit id="th_tablename">
           <source>Table Name</source>
           
        </trans-unit>
        <trans-unit id="th_title">
           <source>Title</source>
           
        </trans-unit>
        <trans-unit id="th_type">
           <source>Type</source>
           
        </trans-unit>
        <trans-unit id="th_show">
           <source>Show</source>
           
        </trans-unit>
        <trans-unit id="th_hide">
           <source>Hide</source>
           
        </trans-unit>
        <trans-unit id="th_uniquecols"><source>Unique columns</source></trans-unit>
        <trans-unit id="th_upload_fpile"><source>Project file upload</source></trans-unit>
        <trans-unit id="th_username"><source>User Name</source></trans-unit>
        <trans-unit id="th_view">
           <source>View</source>
           
        </trans-unit>
        <trans-unit id="toggledatatable">
           <source>Show/Hide Table</source>
           
        </trans-unit>
        <trans-unit id="uproject_add_permission"><source>Add permission</source></trans-unit>
        <trans-unit id="uproject_add_project"><source>Add project</source></trans-unit>
        <trans-unit id="uproject_add_existing_project"><source>Add existing project</source></trans-unit>
        <trans-unit id="uright_add_condition"><source>Add condition</source></trans-unit>
        <trans-unit id="uright_add"><source>Set permission</source></trans-unit>
        <trans-unit id="user_create_button">
           <source>Create user</source>
           
        </trans-unit> 
        <trans-unit id="user_update_button">
        <source>Update user</source>
           
        </trans-unit>
        <trans-unit id="settings_update_button">
           <source>Update settings</source>
           
        </trans-unit>
        <trans-unit id="settings_not_found">
           <source>User settings not found in database</source>
           
        </trans-unit>
        <trans-unit id="yes"><source>YES</source></trans-unit>
        <trans-unit id="noscript">
          <source>javascript is deactivated, this site can't run properly! Please activate javascript to run this site!</source>
          
        </trans-unit>
        <trans-unit id="login_txt">
           <source>Login</source>
           
        <target xml:lang="vi">Tên đăng nhập</target></trans-unit>
        <trans-unit id="login_button">
           <source>Sign in</source>
           
        <target xml:lang="vi">Đăng nhập</target></trans-unit> 
        <trans-unit id="login0">
           <source>Login</source>
           
        <target xml:lang="vi">Tên đăng nhập</target></trans-unit>
        <trans-unit id="password0">
           <source>Password</source>
           
        <target xml:lang="vi">Mật khẩu</target></trans-unit>
        <trans-unit id="remember">
           <source>Remember me</source>
           
        <target xml:lang="vi">Ghi nhớ tôi</target></trans-unit>
        <trans-unit id="login_success0">
           <source>Successfully logged in.</source>
           
        <target xml:lang="vi">Đã đăng nhập thành công</target></trans-unit>
        <trans-unit id="nav_data">
           <source>Data Maintenance</source>
           
        <target xml:lang="vi"/></trans-unit> 
        <trans-unit id="nav_user">
           <source>User Administration</source>
           
        <target xml:lang="vi">Quản lý người dùng</target></trans-unit> 
        <trans-unit id="nav_project">
           <source>Projects</source>
           
        </trans-unit> 
        <trans-unit id="nav_role">
           <source>Role Administration</source>
           
        </trans-unit> 
        <trans-unit id="nav_logout">
           <source>Logout</source>
           
        </trans-unit> 
        <trans-unit id="nav_geodata">
           <source>Geo Data</source>
           
        <target xml:lang="vi">Bảng đồ nông trại</target></trans-unit> 
        <trans-unit id="nav_reports">
           <source>Reports</source>
           
        <target xml:lang="vi">Báo cáo</target></trans-unit> 
        <trans-unit id="nav_logs">
           <source>Log Files</source>
           
        </trans-unit> 
        <trans-unit id="nav_settings">
           <source>Settings</source>
           
        <target xml:lang="vi"/></trans-unit> 
        <trans-unit id="cancel_button">
           <source>Back</source>
           
        </trans-unit> 
        <trans-unit id="bd_update_button">
           <source>Update book</source>
           
        </trans-unit> 
        <trans-unit id="bd_create_button">
           <source>Add book</source>
           
        </trans-unit> 
        <trans-unit id="bd_import_button">
           <source>Import book</source>
           
        </trans-unit> 
        <trans-unit id="bd_download_button">
           <source>Import book</source>
           
        </trans-unit> 
        <trans-unit id="pd_import_button">
           
        </trans-unit> 
        <trans-unit id="pd_download_button">
           
        </trans-unit> 
        <trans-unit id="bd_xliff_button">
           
        </trans-unit> 
        <trans-unit id="bdpage_add_button">
           
        </trans-unit> 
        <trans-unit id="data_import_button">
           
        </trans-unit> 
        <trans-unit id="data_addrow_button">
           <source>Add row</source>
           
        </trans-unit> 
        <trans-unit id="data_download_button">
           
        </trans-unit> 
        <trans-unit id="data_csvexport_button">
           <source>Download table data</source>
           
        </trans-unit> 
        <trans-unit id="data_csvimport_button">
           <source>Import table data</source>
           
        </trans-unit> 
        <trans-unit id="datarow_add_button">
           <source>Add row</source>
           
        </trans-unit> 
        <trans-unit id="datarow_update_button">
           <source>Update row</source>
           
        </trans-unit> 
        <trans-unit id="th_synctype">
           
        </trans-unit> 
        <trans-unit id="th_selectpage">
           
        </trans-unit> 
        <trans-unit id="th_showinsummary">
           
        </trans-unit> 
        <trans-unit id="th_mandatory">
           <source>Mandatory</source>
           
        </trans-unit> 
        <trans-unit id="th_javascript">
           
        </trans-unit> 
        <trans-unit id="th_pagebreak">
           
        </trans-unit> 
        <trans-unit id="option_subpage">
           
        </trans-unit> 
        <trans-unit id="option_downloadonly">
           
        </trans-unit> 
        <trans-unit id="option_uploadonly">
           
        </trans-unit> 
        <trans-unit id="option_uploadanddownload">
           
        </trans-unit> 
        <trans-unit id="th_reportdesc">
           
        </trans-unit> 

        <trans-unit id="th_tablename0">
           <source>Table Name</source>
        </trans-unit>
        <trans-unit id="dlg0">
           <source>OK</source>
        </trans-unit>
        <trans-unit id="dlg1">
           <source>Cancel</source>
           
        </trans-unit>
        <trans-unit id="dlg2">
           <source>Yes</source>
           
        </trans-unit>
        <trans-unit id="dlg3">
           <source>No</source>
           
        </trans-unit>
        <trans-unit id="dlg4">
          <source>Save</source>
          
        </trans-unit>
        <trans-unit id="dlg5">
          <source>Add</source>
          
        </trans-unit>
        <trans-unit id="dlg6">
          <source>Move</source>
          
        </trans-unit>
        <trans-unit id="dlg7">
          <source>Create</source>
          
        </trans-unit>
        <trans-unit id="dlg8">
          <source>Rename</source>
          
        </trans-unit>
        <trans-unit id="dlg9">
          <source>Search</source>
          
        </trans-unit>
        <trans-unit id="logintitle0">
          <source>KIPUS Admin Login</source>
        <target xml:lang="vi"/></trans-unit>
        <trans-unit id="title0">
          <source>KIPUS Admin Dashboard</source>
        </trans-unit>
        <trans-unit id="remember0">
          <source>Remember me</source>
        </trans-unit>
        <trans-unit id="invalid_login0">
          <source>Invalid login, please use a login with valid credentials.</source>
           
        </trans-unit>
        <trans-unit id="invalid_login1">
          <source>Invalid login, user has no admin rights.</source>
        </trans-unit>
        <trans-unit id="invalid_login2">
          <source>Invalid login, user has no report viewing rights.</source>
        </trans-unit>
      
      
        <trans-unit id="bc_error0">
          <source>Error on backendCall: </source>
        </trans-unit>
        <trans-unit id="role_delete0">
          <source>Do you really want to delete this role?</source>
        </trans-unit>
        <trans-unit id="role_delete1">
          <source>Role successfully deleted.</source>
        </trans-unit>
        <trans-unit id="role_delete2">
          <source>Do you really want to delete this role? Warning: role is used by user(s) {1}.</source>
        </trans-unit>
        <trans-unit id="role_delete3">
          <source>Do you really want to delete this user from role?</source>
        </trans-unit>
      
      
        <trans-unit id="role_create0">
          <source>Name, Title and Project are mandatory fields.</source>
        </trans-unit>
        <trans-unit id="role_create1">
          <source>Role successfully created.</source>
        </trans-unit>
      
      
        <trans-unit id="role_update0">
          <source>Role successfully updated.</source>
        </trans-unit>
      
      
        <trans-unit id="user_delete0">
          <source>Do you really want to delete the user {1}?</source>
        </trans-unit>
        <trans-unit id="user_delete1">
          <source>User successfully deleted.</source>
        </trans-unit>
      
      
        <trans-unit id="new_user0">
          <source>New User</source>
        </trans-unit>
      
      
        <trans-unit id="data_clear0">
          <source>Do you really want to clear this table (delete all content of this table)?</source>
        </trans-unit>
        <trans-unit id="data_clear1">
          <source>Table successfully cleared.</source>
        </trans-unit>
      
      
        <trans-unit id="datarow_delete0">
          <source>Do you really want to delete this row?</source>
        </trans-unit>
        <trans-unit id="datarow_delete1">
          <source>Row successfully deleted.</source>
        </trans-unit>
      
      
        <trans-unit id="data_download0">
          <source>Table Name is a mandatory field.</source>
        </trans-unit>
        <trans-unit id="data_download1">
          <source>Table Data successfully downloaded.</source>
        </trans-unit>
      
      
        <trans-unit id="data_csvexport0">
          <source>Table Name is a mandatory field.</source>
        </trans-unit>
        <trans-unit id="data_csvexport1">
          <source>Table Data successfully downloaded as CSV.</source>
        </trans-unit>
      
      
        <trans-unit id="data_csvimport0">
          <source>Please choose a CSV file to import.</source>
        </trans-unit>
        <trans-unit id="data_csvimport1">
          <source>Data successfully imported from CSV.</source>
        </trans-unit>
        <trans-unit id="data_csvimport2">
          <source>Data could not be imported, unable to read CSV file.</source>
        </trans-unit>
        <trans-unit id="data_csvimport3">
          <source>Table Name is a mandatory field.</source>
        </trans-unit>
        <trans-unit id="data_csvimport4">
          <source>Invalid format, first column line is missing in CSV.</source>
        </trans-unit>
        <trans-unit id="data_csvimport5">
          <source>Data could not be imported, no data found in CSV.</source>
        </trans-unit>
        <trans-unit id="data_csvimport6">
          <source>Data could not be imported, columns do not match column header in line </source>
        </trans-unit>
        <trans-unit id="data_csvimport7">
          <source>Table Csv File has wrong extension (needs to be *.csv)</source>
        </trans-unit>
        <trans-unit id="data_csvimport8">
          <source>Data Csv File has wrong extension (needs to be *.datadump.csv)</source>
        </trans-unit>
      
      
        <trans-unit id="user_create0">
          <source>Login, Display Name and Password are mandatory fields.</source>
        </trans-unit>
        <trans-unit id="user_create1">
          <source>Password and confirmation does not match.</source>
        </trans-unit>
        <trans-unit id="user_create2">
          <source>User successfully created.</source>
        </trans-unit>
      
      
        <trans-unit id="user_update0">
          <source>User successfully updated.</source>
        </trans-unit>
        <trans-unit id="user_update1">
          <source>Password and confirmation does not match.</source>
        </trans-unit>
      
      
        <trans-unit id="project_create0">
          <source>Name is mandatory field.</source>
        </trans-unit>
        <trans-unit id="project_create1">
          <source>Project successfully created.</source>
        </trans-unit>
        <trans-unit id="project_create2">
                    <source>Prefix is mandatory field, 5 characters maximum.</source>
        </trans-unit>
      
      
        <trans-unit id="project_download0">
          <source>Project Id is mandatory field.</source>
        </trans-unit>
        <trans-unit id="project_download1">
          <source>Project successfully downloaded.</source>
        </trans-unit>
      
      
        <trans-unit id="project_import0">
          <source>Please choose a project file (.zip) to import.</source>
        </trans-unit>
        <trans-unit id="project_import1">
          <source>Project successfully imported.</source>
        </trans-unit>
        <trans-unit id="project_import2">
          <source>Project could not be imported, unable to read file.</source>
        </trans-unit>
      
      
        <trans-unit id="project_update0">
          <source>Project Id and Name are mandatory fields.</source>
        </trans-unit>
        <trans-unit id="project_update1">
          <source>Project successfully updated.</source>
        </trans-unit>
      
      
        <trans-unit id="project_delete0">
          <source>Do you really want to delete this project and all it's books and files?</source>
        </trans-unit>
        <trans-unit id="project_delete1">
          <source>Project successfully deleted.</source>
        </trans-unit>
      
      
        <trans-unit id="pfile_delete0">
          <source>Do you really want to delete this file?</source>
        </trans-unit>
        <trans-unit id="pfile_delete1">
          <source>File successfully deleted.</source>
        </trans-unit>
      
      
        <trans-unit id="upload_pfile0">
          <source>Please choose a file to upload.</source>
        </trans-unit>
        <trans-unit id="upload_pfile1">
          <source>File successfully uploaded to project.</source>
        </trans-unit>
        <trans-unit id="upload_pfile2">
          <source>File could not be uploaded, unable to read file.</source>
        </trans-unit>
        <trans-unit id="upload_pfile3">
          <source>Max Filesize exceeded (maxsize={1} bytes).</source>
        </trans-unit>
      
      
        <trans-unit id="datarow_filter0">
          <source>Search in the database table {1}</source>
          
        </trans-unit>
        <trans-unit id="datarow_filter1">
          <source>Fulltext search</source>
          
        </trans-unit>
        <trans-unit id="datarow_filter2">
          <source>Search with WHERE clause (SQL)</source>
          
        </trans-unit>
        <trans-unit id="datarow_filter3">
          <source>Either full text search or SQL query has to be set for search.</source>
        </trans-unit>
        <trans-unit id="datarow_filter4">
          <source>{1} column details</source>
          
        </trans-unit>
        <trans-unit id="datarow_filter5">
          <source>Column search</source>
          
        </trans-unit>
      
      
        <trans-unit id="datarow_update0">
          <source>Data row successfully updated.</source>
        </trans-unit>
        <trans-unit id="datarow_update1">
          <source>Table Name and Id is mandatory.</source>
        </trans-unit>
      
      
        <trans-unit id="datarow_create0">
          <source>Table Name is a mandatory field.</source>
        </trans-unit>
        <trans-unit id="datarow_create1">
          <source>Data row successfully created.</source>
        </trans-unit>
      
      
        <trans-unit id="data_import0">
          <source>Please choose a Data file to import.</source>
        </trans-unit>
        <trans-unit id="data_import1">
          <source>Data successfully imported.</source>
        </trans-unit>
        <trans-unit id="data_import2">
          <source>Data could not be imported, unable to read file.</source>
        </trans-unit>
        <trans-unit id="data_import3">
          <source>Data could not be imported, invalid format.</source>
        </trans-unit>
      
      
        <trans-unit id="new_page0">
          <source>New Page Definition</source>
        </trans-unit>
      
      
        <trans-unit id="pd_create0">
          <source>Table Name and Display Name are mandatory fields.</source>
        </trans-unit>
        <trans-unit id="pd_create1">
          <source>Page definition successfully created.</source>
        </trans-unit>
        <trans-unit id="pd_create2">
          <source>Table already exists.</source>
        </trans-unit>
        <trans-unit id="pd_create3">
          <source>If page type is 'Quiz', table name has to start with 'QUIZ_'.</source>
        </trans-unit>
      
      
        <trans-unit id="pd_delete0">
          <source>Do you really want to delete this page definition and all its attributes?</source>
        </trans-unit>
        <trans-unit id="pd_delete1">
          <source>Page definition successfully deleted.</source>
        </trans-unit>
      
      
        <trans-unit id="pd_update0">
          <source>Page definition successfully updated.</source>
        </trans-unit>
        <trans-unit id="pd_update1">
          <source>Table Name and Display Name are mandatory fields.</source>
        </trans-unit>
      
      
        <trans-unit id="pdattr_create0">
          <source>Column Name, Display Name and Column Order are mandatory fields.</source>
        </trans-unit>
        <trans-unit id="pdattr_create1">
          <source>Page attribute successfully created.</source>
        </trans-unit>
        <trans-unit id="pdattr_create2">
          <source>Source page and prefix are mandatory fields.</source>
        </trans-unit>
        <trans-unit id="pdattr_create3">
          <source>Source page not found.</source>
        </trans-unit>
      
      
        <trans-unit id="pdattr_delete0">
          <source>Do you really want to delete this attribute in all referenced tables?</source>
        </trans-unit>
        <trans-unit id="pdattr_delete1">
          <source>Page attribute successfully deleted.</source>
        </trans-unit>
      
      
        <trans-unit id="pdattr_update0">
          <source>Page attribute successfully updated.</source>
        </trans-unit>
        <trans-unit id="pdattr_update1">
          <source>Column Name, Display Name and Column Order are mandatory fields.</source>
        </trans-unit>
        <trans-unit id="pdattr_update2">
          <source>Cannot change constrainttype, as it would change DB column type.</source>
        </trans-unit>
      
      
        <trans-unit id="pdattr_rename0">
          <source>Page attribute successfully renamed.</source>
        </trans-unit>
        <trans-unit id="pdattr_rename1">
          <source>Column Name may not be empty.</source>
        </trans-unit>
        <trans-unit id="pdattr_rename2">
          <source>Column Name is already used in this project (not renamed).</source>
        </trans-unit>
        <trans-unit id="pdattr_rename3">
          <source>Column Name and new Column Name are identical (not renamed).</source>
        </trans-unit>
        <trans-unit id="pdattr_rename4">
          <source>Warning: this attribute may already be referenced in reports or client logic.<br/></source>
        </trans-unit>
           Do you really want to rename this attribute? This will be reported!
      
      
        <trans-unit id="bd_create0">
          <source>Name is a mandatory field.</source>
        </trans-unit>
        <trans-unit id="bd_create1">
          <source>Book definition successfully created.</source>
        </trans-unit>
      
      
        <trans-unit id="external_create0">
          <source>All fields except of Filter are mandatory fields.</source>
        </trans-unit>
        <trans-unit id="external_create1">
          <source>External table successfully added.</source>
        </trans-unit>
      
      
        <trans-unit id="external_update0">
          <source>External update successful.</source>
        </trans-unit>
      
      
        <trans-unit id="external_delete0">
          <source>Do you really want to delete the external table?</source>
        </trans-unit>
        <trans-unit id="external_delete1">
          <source>External successfully deleted.</source>
        </trans-unit>
      
      
        <trans-unit id="bd_download0">
          <source>Book definition Id is a mandatory field.</source>
        </trans-unit>
        <trans-unit id="bd_download1">
          <source>Book definition successfully downloaded.</source>
        </trans-unit>
      
      
        <trans-unit id="bd_import0">
          <source>Please choose a book definition file to import.</source>
        </trans-unit>
        <trans-unit id="bd_import1">
          <source>Book definition successfully imported.</source>
        <target xml:lang="vi"/></trans-unit>
        <trans-unit id="bd_import2">
          <source>Book definition could not be imported, unable to read file.</source>
        </trans-unit>
        <trans-unit id="bd_import3">
          <source>Book definition could not be imported, invalid format.</source>
        </trans-unit>
      
      
        <trans-unit id="pd_import0">
          <source>Please choose a page definition file to import.</source>
        </trans-unit>
        <trans-unit id="pd_import1">
          <source>Page definition successfully imported.</source>
        </trans-unit>
        <trans-unit id="pd_import2">
          <source>Page definition could not be imported, unable to read file.</source>
        </trans-unit>
        <trans-unit id="pd_import3">
          <source>Page definition could not be imported, invalid format.</source>
        </trans-unit>
      
      
        <trans-unit id="pd_download0">
          <source>Page definition Id is a mandatory field.</source>
        <target xml:lang="vi"/></trans-unit>
        <trans-unit id="pd_download1">
          <source>Page definition successfully downloaded.</source>
        </trans-unit>
      
      
        <trans-unit id="bd_delete0">
          <source>Do you really want to delete this book definition?</source>
        </trans-unit>
        <trans-unit id="bd_delete1">
          <source>Book definition successfully deleted.</source>
        </trans-unit>
      
      
        <trans-unit id="bd_update0">
          <source>Book definition successfully updated.</source>
        </trans-unit>
        <trans-unit id="bd_update1">
          <source>Name is a mandatory field.</source>
        </trans-unit>
      
      
        <trans-unit id="bdpage_add0">
          <source>Book Id and Page Id are mandatory fields.</source>
        </trans-unit>
        <trans-unit id="bdpage_add1">
          <source>Bookpage successfully added.</source>
        </trans-unit>
      
      
        <trans-unit id="bdpage_delete0">
          <source>Do you really want to remove this page from the book?</source>
        </trans-unit>
        <trans-unit id="bdpage_delete1">
          <source>Page successfully removed from book.</source>
        </trans-unit>
        <trans-unit id="bdpage_delete2">
          <source>Book Id and Page Id are mandatory fields.</source>
        </trans-unit>
      
      
        <trans-unit id="xliffgen0">
          <source>Project Id is a mandatory field.</source>
        </trans-unit>
        <trans-unit id="xliffgen1">
          <source>Xliff successfully generated.</source>
        </trans-unit>
      
      
        <trans-unit id="pbook_add0">
          <source>Project Id and Book Id are mandatory fields.</source>
        </trans-unit>
        <trans-unit id="pbook_add1">
          <source>Book successfully added to project.</source>
        </trans-unit>
      
      
        <trans-unit id="pbook_delete0">
          <source>Do you really want to delete this book?</source>
        </trans-unit>
        <trans-unit id="pbook_delete1">
          <source>Book successfully deleted.</source>
        </trans-unit>
      
      
        <trans-unit id="uproject_add0">
          <source>Login and Project Id are mandatory fields.</source>
        </trans-unit>
        <trans-unit id="uproject_add1">
          <source>Project successfully added to user.</source>
        </trans-unit>
      
      
        <trans-unit id="uproject_delete0">
          <source>Do you really want to remove this project from the user?</source>
        </trans-unit>
        <trans-unit id="uproject_delete1">
          <source>Project successfully removed from user.</source>
        </trans-unit>
      
      
        <trans-unit id="bookdata_delete0">
          <source>Do you really want to delete this record including all bookdata?</source>
        </trans-unit>
        <trans-unit id="bookdata_delete1">
          <source>Commit changes?</source>
        </trans-unit>
        <trans-unit id="bookdata_delete2">
          <source>Save changes in {1} data set?</source>
        </trans-unit>
        <trans-unit id="bookdata_delete3">
          <source>Do you really want to delete this data set and assign all bookdata to the data set on the {1} <i style="color: #fbe074;" class="glyph glyphicon glyphicon-arrow-{1}"/> side?</source>
        </trans-unit>
        <trans-unit id="image_upload0">
          <source>Choose Image File to upload</source>
        </trans-unit>
        <trans-unit id="image_upload1">
          <source>Upload Image</source>
        </trans-unit>
        <trans-unit id="image_upload2">
          <source>Table Name and Image Name are mandatory field.</source>
        </trans-unit>
        <trans-unit id="image_upload3">
          <source>Image could not be uploaded, unable to read image file.</source>
        </trans-unit>
        <trans-unit id="image_upload4">
          <source>Image successfully uploaded.</source>
        </trans-unit>
        <trans-unit id="regexp0">
          <source>Wrong format, please correct above errors first!</source>
        </trans-unit>
        <trans-unit id="tooltip0">
          <source>Only characters A-Z, 0-9 and _ are allowed plus may not start with 0-9!</source>
        </trans-unit>
        <trans-unit id="tooltip1">
          <source>Values may be approximations. Admin Dashboard uses a quick method to get the row count, and this method only returns an approximate count in the case of InnoDB tables.</source>
        </trans-unit>
        <trans-unit id="tooltip2">
          <source>Called if the content of the field changes.</source>
        </trans-unit>
        <trans-unit id="tooltip3">
          <source>Called if save is called, returns false if the check failed.</source>
        </trans-unit>
        <trans-unit id="tooltip4">
          <source><b>Syntax:</b> <i>FilterEntry</i>[:<i>FilterColumn</i>]=<i>Regexp</i><br/><br/><i>FilterEntry</i> is the name of a field on this page or on the header page.<br/>
             This value must match the <i>Regexp</i>.<br/>
        <br/>  If <i>FilterColumn</i> is specified, the
             <i>FilterEntry</i> must be of type "Single Value from table", and <i>FilterColumn</i>
             must be a valid column in this table.<br/>The Value of this column is taken
             for comparison with the <i>Regexp</i>.
          </source>
        <target xml:lang="vi"/></trans-unit>
        <trans-unit id="tooltip5">
          <source>Draw one border around this and the next field.</source>
        </trans-unit>
        <trans-unit id="tooltip6">
          <source><b>Syntax:</b> <i>TableName</i> [<i>ColumnName</i>=<i>FilterEntry</i>[:<i>FilterColumn</i>]]<br/><br/>
             Display the DISPLAYNAME column values from <i>TableName</i>.<br/>
            <br/>
             If <i>ColumnName=</i> is specified, then filter the lines.<br/>
             <i>ColumnName</i> must be a column in <i>TableName</i>.<br/>
             <br/>
             If <i>FilterEntry</i> is enclosed in "" then only lines with this literal value
             are shown, else another value on this page or the header page is searched
             with the name of <i>FilterEntry</i>.<br/>
             <br/>
             If <i>FilterColumn</i> is specified, the <i>FilterEntry</i> must be of type "Single Value
             from table", and <i>FilterColumn</i> must be a valid column in this table.
          </source>
        </trans-unit>
        <trans-unit id="tooltip7">
          <source>"a,b c,d", where a,b,c,d is a columnName followed by an optional "=RegExp", and interpreted as a AND b OR c AND d ...</source>
        </trans-unit>
        <trans-unit id="tooltip8">
          <source>All of the conditions must be true at the same
                  time for the same book header page
          </source>
        </trans-unit>
        <trans-unit id="tooltip9">
          <source>The header page should contain only one attribute,
                  which is a link to the parent header
          </source>
        </trans-unit>
        <trans-unit id="tooltip10">
          <source>Comma separated list of Column Names, with
                  optional =DESTINATION COLUMNNAME after each Column Name
        </source>
        </trans-unit>
        <trans-unit id="tooltip11">
          <source>If last is chosen, use to the value of the last historic entry with the same name.</source>
        </trans-unit>
        <trans-unit id="tooltip12">
          <source>Permission is a combination of a role and zero or or more conditions. You have to first add a project to project list
                  before adding a permission.
          </source>
        </trans-unit>
        <trans-unit id="tooltip13">
          <source>"All Projects" and the right UserFronted exclude each other.</source>
        </trans-unit>
        <trans-unit id="tooltip14">
          <source>Only characters A-Z, 0-9 and _ are allowed plus may not start with 0-9! (5 characters allowed maximum)</source>
        </trans-unit>
        <trans-unit id="tooltip15">
          <source>source:TABLE (type BODY)<br/>
          target:TABLE (BODY, hidden by subpageparam)<br/>
          display:comma separated list of source columns to show in 
          the table<br/>
          prefix:each target column is prefixed by this<br/>
          filter:comma separated col=val for source<br/>
        </source>
        </trans-unit>
        <trans-unit id="tooltip16">
          <source>
          {TABLENAME:id} is replaced by DISPLAYNAME
          (LU_DEFAULTS@kipus_tst)<br/>
          {last} take the last filled value<br/>
          {code} will be executed<br/>
          <br/>
        </source>
        </trans-unit>
        <trans-unit id="tooltip17">
          <source>
          target:TABLE (BODY, hidden by subpageparam)<br/>
          prefix:each target column is prefixed by this<br/>
          noDelete:if set to true, hide the delete button<br/>
          expandColumn:generate all entries for a given column<br/>
          maxNo:maximum Number of entries<br/>
          </source>
        </trans-unit>
          
        <trans-unit id="tooltip18">
          <source>
          &lt;width&gt; x &lt;heigth&gt; (resize to maximum width or heigth)<br/>
          Optional: capture:both, capture:user, capture:environment (force using a camera on mobile)
          </source>
        </trans-unit>
          
        <trans-unit id="tooltip19">
          <source>
          Possible options:<br/>
          ADDRESS:colname<br/>
          COMPUTED:colname<br/>
          ELEVATION:colname<br/>
          AREA:colname<br/>
          SHAPE:colname<br/>
          TIMESTAMP:colname<br/>
          AUTOFILL:1<br/>
        </source>
        </trans-unit>
        <trans-unit id="leave0">
          <source>Please confirm you want to leave this page.</source>
        </trans-unit>
        <trans-unit id="filter0">
          <source>filter</source>
        </trans-unit>
        <trans-unit id="filter1">
          <source>clear filter</source>
          
        </trans-unit>
        <trans-unit id="filter2">
          <source>Filter text (space-separated), press return or filter button to filter</source>
          
        </trans-unit>
        <trans-unit id="filter3">
          <source>filtered by </source>
          
        </trans-unit>
        <trans-unit id="filter4">
          <source>Hide filter</source>
          
        </trans-unit>
        <trans-unit id="filter5">
          <source>Show filter</source>
          
        </trans-unit>
        <trans-unit id="mandatory0">
          <source>Mandatory field</source>
        </trans-unit>
        <trans-unit id="constraintparam0">
          <source>max-width x max-height (optional)</source>
        </trans-unit>
        <trans-unit id="constraintparam1">
          <source>comma separated values</source>
        </trans-unit>
        <trans-unit id="constraintparam2">
          <source>tableName [ColumnName=FilterEntry[:FilterColumn]]</source>
        </trans-unit>
        <trans-unit id="constraintparam3">
          <source>executed for non-empty fields.</source>
        </trans-unit>
        <trans-unit id="constraintparam4">
          <source>minimum,maximum[,decimals]</source>
        </trans-unit>
        <trans-unit id="constraintparam5">
          <source>cols x rows (optional)</source>
        </trans-unit>
        <trans-unit id="constraintparam6">
          <source>was gps, unused now, see tooltip19</source>
        </trans-unit>
        <trans-unit id="constraintparam7">
          <source>imageTableName:id</source>
        </trans-unit>
        <trans-unit id="constraintparam8">
          <source>maxSizeInBytes .xls .docx .pdf AllowDownload (optional)</source>
        </trans-unit>
        <trans-unit id="constraintparam9">
          <source>source target prefix display filter</source>
        </trans-unit>
        <trans-unit id="constraintparam10">
          <source>target:TABLENAME prefix:COLPREFIX</source>
        </trans-unit>
      
      
        <trans-unit id="selectionrequired">
          <source>Please select at least one</source>
        </trans-unit>
      
      
        <trans-unit id="All">
          <source>All</source>
        </trans-unit>
      
        <trans-unit id="Jan">
          <source>Jan</source>
        </trans-unit>
        <trans-unit id="Feb">
          <source>Feb</source>
        </trans-unit>
        <trans-unit id="Mar">
          <source>Mar</source>
        </trans-unit>
        <trans-unit id="Apr">
          <source>Apr</source>
        </trans-unit>
        <trans-unit id="May">
          <source>May</source>
        </trans-unit>
        <trans-unit id="Jun">
          <source>Jun</source>
        </trans-unit>
        <trans-unit id="Jul">
          <source>Jul</source>
        </trans-unit>
        <trans-unit id="Aug">
          <source>Aug</source>
        </trans-unit>
        <trans-unit id="Sep">
          <source>Sep</source>
        </trans-unit>
        <trans-unit id="Oct">
          <source>Oct</source>
        </trans-unit>
        <trans-unit id="Nov">
          <source>Nov</source>
        </trans-unit>
        <trans-unit id="Dec">
          <source>Dec</source>
        </trans-unit>
      
        <trans-unit id="Q1">
          <source>Q1</source>
        </trans-unit>
        <trans-unit id="Q2">
          <source>Q2</source>
        </trans-unit>
        <trans-unit id="Q3">
          <source>Q3</source>
        </trans-unit>
        <trans-unit id="Q4">
          <source>Q4</source>
        </trans-unit>
      
      
        <trans-unit id="name">
          <source>Name</source>
        </trans-unit>
        <trans-unit id="description">
          <source>Description</source>
        </trans-unit>
        <trans-unit id="number">
          <source>Nr</source>
        </trans-unit>
        <trans-unit id="Year">
          <source>Year</source>
        </trans-unit>
        <trans-unit id="Quarter">
          <source>Quarter</source>
        </trans-unit>
        <trans-unit id="Month">
          <source>Month</source>
        </trans-unit>
        <trans-unit id="YearFrom">
          <source>Year from</source>
        </trans-unit>
        <trans-unit id="QuarterFrom">
          <source>Quarter from</source>
        </trans-unit>
        <trans-unit id="MonthFrom">
          <source>Month from</source>
        </trans-unit>
        <trans-unit id="YearTo">
          <source>Year to</source>
        </trans-unit>
        <trans-unit id="QuarterTo">
          <source>Quarter to</source>
        </trans-unit>
        <trans-unit id="MonthTo">
          <source>Month to</source>
        </trans-unit>
        <trans-unit id="region">
          <source>Region</source>
        </trans-unit>
        <trans-unit id="organisation">
          <source>Organisation</source>
        </trans-unit>
        <trans-unit id="farm">
          <source>Farm</source>
        </trans-unit>
        <trans-unit id="field">
          <source>Field</source>
        </trans-unit>
        <trans-unit id="crop">
          <source>Crop</source>
        </trans-unit>
        <trans-unit id="cropVariety">
          <source>Crop variety</source>
        </trans-unit>
        <trans-unit id="ViewAs">
          <source>View as</source>
        </trans-unit>
        <trans-unit id="Table">
          <source>Table</source>
        </trans-unit>
        <trans-unit id="BarChart">
          <source>Bar chart</source>
        </trans-unit>
        <trans-unit id="LineChart">
          <source>Line chart</source>
        </trans-unit>
        <trans-unit id="PieChart">
          <source>Pie chart</source>
        </trans-unit>
        <trans-unit id="TimeseriesChart">
          <source>Time series chart</source>
        </trans-unit>
        <trans-unit id="StackedBarChart">
          <source>Stacked Bar chart</source>
        </trans-unit>
        <trans-unit id="AggregatedBy">
          <source>Aggregated by</source>
        </trans-unit>
        <trans-unit id="CountryCrop">
          <source>Country and Crop</source>
        </trans-unit>
        <trans-unit id="RegionCrop">
          <source>Region and Crop</source>
        </trans-unit>
        <trans-unit id="OrganisationCrop">
          <source>Organisation and Crop</source>
        </trans-unit>
        <trans-unit id="FarmCrop">
          <source>Farm and Crop</source>
        </trans-unit>
        <trans-unit id="RegionAssessmentLevel">
          <source>Region and Assessment Level</source>
        </trans-unit>
        <trans-unit id="CountryFertilizer">
          <source>Country and Fertilizer</source>
        </trans-unit>
        <trans-unit id="RegionFertilizer">
          <source>Region and Fertilizer</source>
        </trans-unit>
        <trans-unit id="OrganisationFertilizer">
          <source>Organisation and Fertilizer</source>
        </trans-unit>
        <trans-unit id="FarmFertilizer">
          <source>Farm and Fertilizer</source>
        </trans-unit>
        <trans-unit id="FieldFertilizer">
          <source>Field and Fertilizer</source>
        </trans-unit>
        <trans-unit id="CropFertilizer">
          <source>Crop and Fertilizer</source>
        </trans-unit>
        <trans-unit id="CountryPesticide">
          <source>Country and Plant Protection</source>
        </trans-unit>
        <trans-unit id="RegionPesticide">
          <source>Region and Plant Protection</source>
        </trans-unit>
        <trans-unit id="OrganisationPesticide">
          <source>Organisation and Plant Protection</source>
        </trans-unit>
        <trans-unit id="FarmPesticide">
          <source>Farm and Plant Protection</source>
        </trans-unit>
        <trans-unit id="FieldPesticide">
          <source>Field and Plant Protection</source>
        </trans-unit>
        <trans-unit id="CropPesticide">
          <source>Crop and Plant Protection</source>
        </trans-unit>
        <trans-unit id="th_orgs">
          <source>Farm Organization</source>
          <target xml:lang="vi">Tên Tổ chức</target>
        </trans-unit>
        <trans-unit id="org_clear_filter_button">
          <source>Clear Filter</source>
          <target xml:lang="vi">Bỏ lượt</target>
        </trans-unit>
        <trans-unit id="org_filter_button">
          <source>Filter Organization</source>
          <target xml:lang="vi">Lượt Tổ chức</target>
        </trans-unit>
        <trans-unit id="th_reportnumber">
          <source>Nr</source>
          <target xml:lang="vi">STT</target>
        </trans-unit>
        <trans-unit id="th_reportname">
          <source>Name</source>
          <target xml:lang="vi">Tên</target>
        </trans-unit>
        <trans-unit id="th_reportdesc">
          <source>Description</source>
          <target xml:lang="vi">Miêu tả</target>
        </trans-unit>
        <trans-unit id="th_reportmodified">
          <source>Modified</source>
          <target xml:lang="vi">Được thay đổi</target>
        </trans-unit>
    </body>
  </file>
</xliff>
